skymask_py-0.1.0.dist-info/METADATA
skymask_py-0.1.0.dist-info/WHEEL
skymask_py/__init__.py
skymask_py/__init__.pyi
skymask_py/py.typed
skymask_py/skymask_py.cpython-38-arm-linux-gnueabihf.so
skymask_py-0.1.0.dist-info/RECORD
